{
  "lesson-1": {
    "id": "lesson-1",
    "title": "Into the Unknown",
    "time": [
      [0, 0],
      [0, 0]
    ],
    "nodeText": "Take the first step of your learning journey into the dark, winding forest of Chess.",
    "reward": [],
    "prereq": "",
    "opponent": "",
    "boss": false,
    "theme": "black",
    "panels": {
      "panel-1": {
        "fen": "b2r3r/k4p1p/p2q1np1/NppP4/3p1Q2/P4PPB/1PP4P/1K1RR3 w - - 1 24",
        "fenHistory": [
          "b2r3r/k4p1p/p2q1np1/NppP4/3p1Q2/P4PPB/1PP4P/1K1RR3 w - - 1 24"
        ],
        "history": [],
        "panelText": "Chess, as well as other disciplines in life, is a deep study. You will face unknowns and you will not always be prepared to handle them. Do you have the courage to take the first step and every step after that?",
        "royalties": {
          "royaltyQ": {},
          "royaltyM": {},
          "royaltyT": {},
          "royaltyV": {},
          "royaltyE": {}
        },
        "arrowsCircles": [],
        "preset": "NORMAL",
        "whiteArcane": {},
        "blackArcane": {},
        "config": {},
        "correctMoves": [],
        "viewOnly": true,
        "orientation": "white"
      },
      "panel-2": {
        "fen": "b2r3r/k4p1p/p2q1np1/NppP4/3R1Q2/P4PPB/1PP4P/1K2R3 b - - 0 24",
        "fenHistory": [
          "b2r3r/k4p1p/p2q1np1/NppP4/3R1Q2/P4PPB/1PP4P/1K2R3 b - - 0 24"
        ],
        "history": [],
        "panelText": "This is not only a game, you will learn about who you are along the way. Don’t get lost in the tangling branches of variations to find that one tactic. See the full picture. Take in what philosophies are offered and pack them in your bag. The game is an entertaining side effect.",
        "arrowsCircles": [
          {
            "orig": "d1",
            "dest": "d4",
            "brush": "green"
          }
        ],
        "royalties": {
          "royaltyQ": {},
          "royaltyT": {},
          "royaltyM": {},
          "royaltyV": {},
          "royaltyE": {}
        },
        "preset": "CLEAR",
        "whiteArcane": {},
        "blackArcane": {},
        "config": {},
        "correctMoves": [],
        "viewOnly": true,
        "orientation": "white"
      }
    }
  },
  "lesson-2": {
    "id": "lesson-2",
    "title": "The Objective",
    "time": [
      [0, 0],
      [0, 0]
    ],
    "nodeText": "What are you fighting for? Learn about why chess is a zero-sum game.",
    "panelText": "",
    "reward": [500, "a", "b", "c"],
    "prereq": "",
    "opponent": "",
    "theme": "",
    "panels": {
      "panel-1": {
        "fen": "8/8/8/8/8/8/8/8 w - - 0 1",
        "fenHistory": ["8/8/8/8/8/8/8/8 w - - 0 1"],
        "history": [],
        "panelText": "What is the goal here? The normal chess ending is checkmate. This happens when a King is attacked and there’s no move to stop it from being captured on the next turn. Take a look the King’s movement now by moving it around the board.",
        "arrowsCircles": [],
        "nodeText": "",
        "reward": [],
        "description": "",
        "opponent": "",
        "prereq": "",
        "royalties": {
          "royaltyQ": {},
          "royaltyT": {},
          "royaltyM": {},
          "royaltyV": {},
          "royaltyE": {}
        },
        "preset": "CLEAR",
        "whiteArcane": {},
        "blackArcane": {},
        "config": {},
        "correctMoves": [],
        "viewOnly": false,
        "orientation": "white"
      },
      "panel-2": {
        "fen": "8/8/8/3k4/5N2/8/8/8 w - - 0 1",
        "fenHistory": ["8/8/8/3k4/5N2/8/8/8 w - - 0 1"],
        "history": [],
        "panelText": "The key mechanic here is attacking the King… this is called check. The side in check is forced to take action. There are at most 3 options to save here: move the King, block the attack, or capture the attacking piece. Depending on the situation you might only have one way out, but keep an eye out for your options.",
        "arrowsCircles": [
          {
            "orig": "f4",
            "dest": "d5",
            "brush": "green"
          }
        ],
        "nodeText": "",
        "reward": [],
        "description": "",
        "opponent": "",
        "prereq": "",
        "royalties": {
          "royaltyQ": {},
          "royaltyT": {},
          "royaltyM": {},
          "royaltyV": {},
          "royaltyE": {}
        },
        "preset": "CLEAR",
        "whiteArcane": {},
        "blackArcane": {},
        "config": {},
        "correctMoves": [],
        "viewOnly": true,
        "orientation": "white"
      }
    },
    "boss": false
  }
}
